qsdsan/__init__.py
qsdsan/_component.py
qsdsan/_components.py
qsdsan/_construction.py
qsdsan/_equipment.py
qsdsan/_impact_indicator.py
qsdsan/_impact_item.py
qsdsan/_lca.py
qsdsan/_process.py
qsdsan/_sanstream.py
qsdsan/_sanunit.py
qsdsan/_tea.py
qsdsan/_transportation.py
qsdsan/_waste_stream.py
qsdsan/stats.py
qsdsan/data/_adm1.xlsx
qsdsan/data/_components.tsv
qsdsan/data/_madm1.xlsx
qsdsan/data/_masm2d.xlsx
qsdsan/data/process_data/_adm1.tsv
qsdsan/data/process_data/_adm1_p_extension.tsv
qsdsan/data/process_data/_asm1.tsv
qsdsan/data/process_data/_asm2d.tsv
qsdsan/data/process_data/_madm1.tsv
qsdsan/data/process_data/_masm2d.tsv
qsdsan/data/process_data/_mmp.tsv
qsdsan/data/process_data/_pm2.tsv
qsdsan/data/process_data/_pm2abaco2_1.tsv
qsdsan/data/process_data/_pm2abaco2_2.tsv
qsdsan/data/process_data/_pm2asm2d.tsv
qsdsan/data/process_data/_pm2asm2d_1.tsv
qsdsan/data/process_data/_pm2asm2d_2.tsv
qsdsan/data/sanunit_data/_anaerobic_baffled_reactor.tsv
qsdsan/data/sanunit_data/_anaerobic_digestion.tsv
qsdsan/data/sanunit_data/_anaerobic_lagoon.tsv
qsdsan/data/sanunit_data/_drying_bed.tsv
qsdsan/data/sanunit_data/_excretion.tsv
qsdsan/data/sanunit_data/_facultative_lagoon.tsv
qsdsan/data/sanunit_data/_inf_dry_2006.tsv
qsdsan/data/sanunit_data/_liquid_treatment_bed.tsv
qsdsan/data/sanunit_data/_murt.tsv
qsdsan/data/sanunit_data/_pit_latrine.tsv
qsdsan/data/sanunit_data/_sedimentation_tank.tsv
qsdsan/data/sanunit_data/_septic_tank.csv
qsdsan/data/sanunit_data/_sludge_pasteurization.tsv
qsdsan/data/sanunit_data/_sludge_separator.tsv
qsdsan/data/sanunit_data/_toilet.tsv
qsdsan/data/sanunit_data/_uddt.tsv
qsdsan/data/sanunit_data/br/_br_carbonizer_base.tsv
qsdsan/data/sanunit_data/br/_br_controls.tsv
qsdsan/data/sanunit_data/br/_br_grinder.tsv
qsdsan/data/sanunit_data/br/_br_hhx.tsv
qsdsan/data/sanunit_data/br/_br_hhx_dryer.tsv
qsdsan/data/sanunit_data/br/_br_housing.tsv
qsdsan/data/sanunit_data/br/_br_ion_exchange.tsv
qsdsan/data/sanunit_data/br/_br_ohx.tsv
qsdsan-1.4.3.dist-info/licenses/LICENSE.txt
qsdsan-1.4.3.dist-info/METADATA
qsdsan-1.4.3.dist-info/WHEEL
qsdsan-1.4.3.dist-info/top_level.txt
qsdsan-1.4.3.dist-info/RECORD
