Metadata-Version: 2.4
Name: qsdsan
Version: 1.4.3
Summary: Quantitative Sustainable Design for sanitation and resource recovery systems
Home-page: https://github.com/QSD-Group/QSDsan
Author: Quantitative Sustainable Design Group
Author-email: quantitative.sustainable.design@gmail.com
License: UIUC
Project-URL: Homepage, https://qsdsan.com
Project-URL: Documentation, https://qsdsan.readthedocs.io
Project-URL: Repository, https://github.com/QSD-Group/QSDsan
Keywords: quantitative sustainable design,sanitation,resource recovery,techno-economic analysis,life cycle assessment
Classifier: License :: OSI Approved :: University of Illinois/NCSA Open Source License
Classifier: Environment :: Console
Classifier: Topic :: Education
Classifier: Topic :: Scientific/Engineering
Classifier: Topic :: Scientific/Engineering :: Chemistry
Classifier: Topic :: Scientific/Engineering :: Mathematics
Classifier: Intended Audience :: Developers
Classifier: Intended Audience :: Education
Classifier: Intended Audience :: Manufacturing
Classifier: Intended Audience :: Science/Research
Classifier: Natural Language :: English
Classifier: Operating System :: OS Independent
Classifier: Programming Language :: Python :: 3.12
License-File: LICENSE.txt
Requires-Dist: biosteam==2.51.19
Requires-Dist: thermosteam==0.51.17
Requires-Dist: matplotlib>=3.3.2
Requires-Dist: pandas>=1.3.2
Requires-Dist: SALib>=1.4.5
Requires-Dist: scikit-learn
Requires-Dist: scipy>=1.7.1
Requires-Dist: seaborn
Requires-Dist: sympy>=1.8
Dynamic: author
Dynamic: author-email
Dynamic: classifier
Dynamic: description
Dynamic: home-page
Dynamic: keywords
Dynamic: license
Dynamic: license-file
Dynamic: project-url
Dynamic: requires-dist
Dynamic: summary
